{
  "version": "7",
  "dialect": "postgresql",
  "entries": [
    {
      "idx": 0,
      "version": "7",
      "when": 1720185690831,
      "tag": "0000_workable_gorgon",
      "breakpoints": true
    },
    {
      "idx": 1,
      "version": "7",
      "when": 1720188701009,
      "tag": "0001_great_magus",
      "breakpoints": true
    },
    {
      "idx": 2,
      "version": "7",
      "when": 1720192330053,
      "tag": "0002_parallel_sasquatch",
      "breakpoints": true
    },
    {
      "idx": 3,
      "version": "7",
      "when": 1720291570665,
      "tag": "0003_redundant_the_anarchist",
      "breakpoints": true
    }
  ]
}